{
  "$schema": "https://raw.githubusercontent.com/dineug/erd-editor/main/json-schema/schema.json",
  "version": "3.0.0",
  "settings": {
    "width": 4000,
    "height": 4000,
    "scrollTop": -100,
    "scrollLeft": -322.9207,
    "zoomLevel": 0.82,
    "show": 431,
    "database": 1,
    "databaseName": "MAIN",
    "canvasType": "ERD",
    "language": 1,
    "tableNameCase": 4,
    "columnNameCase": 2,
    "bracketType": 1,
    "relationshipDataTypeSync": true,
    "relationshipOptimization": false,
    "columnOrder": [
      1,
      2,
      4,
      8,
      16,
      32,
      64
    ],
    "maxWidthComment": -1,
    "ignoreSaveSettings": 0
  },
  "doc": {
    "tableIds": [
      "IVFL0tVOqoKbhTHys2c68",
      "ic8qI8cXoM7FoDHA6eZO2",
      "LQ6xqThd9sB75yziJ29q4",
      "dPNIQ1drtSQcs5zYD5J6k",
      "AblPsS5f9kFkxgnlNHuR4",
      "h5wO3PYGvf-QvEnUodwWD",
      "MZzQgWsKLlCjdaTvkv_5n",
      "PZABfmy4YQI78cd8GmzKI",
      "ljgpQ-ut5b5LoN7vA-yQR",
      "nI60JygSC7yhleBHLTc_E"
    ],
    "relationshipIds": [
      "YtyghDogwvJ3JZTZeYz0H",
      "D-B-0aQD1qJvD6PizE4gx",
      "s3Q9bL-xfkaLt2zN3n2lD",
      "R1oOn_lrzmAo17E1Up3Ye",
      "ojau24ldOTQOe6yNscmGW",
      "Tw-aKEz6HEb7VwFdhW5wL",
      "9uzg_thkkvkO2CZzfIQIo",
      "qDMuPz6jUjd1DgoRAvS09",
      "DNH8VKpvUj_2M8NjpsrM-",
      "EBDhVi0rQCXI6npZn5ENY",
      "GAlHyIcNQf2h2XprNrvaA",
      "X_B49gYJP8Ir3YxUyhfeB"
    ],
    "indexIds": [],
    "memoIds": []
  },
  "collections": {
    "tableEntities": {
      "IVFL0tVOqoKbhTHys2c68": {
        "id": "IVFL0tVOqoKbhTHys2c68",
        "name": "ADMCAT_ENTIDADES",
        "comment": "",
        "columnIds": [
          "a2Ylt0NMtvJaB4V9I-bzp",
          "aJTMV8sFMZRYyeR5iz8Qi",
          "DX0OA5goKXQJeX7f-SeRg",
          "PuRQlQEBGGJI17X9vnYBH",
          "EDrVmf-w0ipe4MZ5NoAJF"
        ],
        "seqColumnIds": [
          "hYEQ0o8cybYRYyJaygNWA",
          "a2Ylt0NMtvJaB4V9I-bzp",
          "5kJQPXpyhUS1doRa_BEKv",
          "aJTMV8sFMZRYyeR5iz8Qi",
          "DX0OA5goKXQJeX7f-SeRg",
          "PuRQlQEBGGJI17X9vnYBH",
          "EDrVmf-w0ipe4MZ5NoAJF"
        ],
        "ui": {
          "x": 511.5048,
          "y": 85.8375,
          "zIndex": 2,
          "widthName": 116,
          "widthComment": 60,
          "color": ""
        },
        "meta": {
          "updateAt": 1730226679195,
          "createAt": 1729267035614
        }
      },
      "ic8qI8cXoM7FoDHA6eZO2": {
        "id": "ic8qI8cXoM7FoDHA6eZO2",
        "name": "TRB_USUARIOS",
        "comment": "",
        "columnIds": [
          "9TMxcuD0BUhpN_NJtKaI_",
          "IYAlhJTjLLLQUrJ-S_j5A",
          "Xq9_PHOLJjaFhQzoVvFzM",
          "9-xFfkpsAbXJQd_HI7g2m",
          "zXKxytADtc7w7wjwUQ4Bx",
          "lVJ7BHwsMrEpcnmh782vG",
          "FPsmcP2g66A0veDbreDWP",
          "yfE7Ssgx-mKwZ3ANDU-mr"
        ],
        "seqColumnIds": [
          "AeuHd-sdgcfEAIFrLRtzc",
          "9TMxcuD0BUhpN_NJtKaI_",
          "IYAlhJTjLLLQUrJ-S_j5A",
          "Xq9_PHOLJjaFhQzoVvFzM",
          "EQwX-3e3hikkLxuLDb8i3",
          "9-xFfkpsAbXJQd_HI7g2m",
          "zXKxytADtc7w7wjwUQ4Bx",
          "lVJ7BHwsMrEpcnmh782vG",
          "FPsmcP2g66A0veDbreDWP",
          "yfE7Ssgx-mKwZ3ANDU-mr"
        ],
        "ui": {
          "x": 508.3868,
          "y": 512.3357,
          "zIndex": 11,
          "widthName": 83,
          "widthComment": 60,
          "color": ""
        },
        "meta": {
          "updateAt": 1730226767752,
          "createAt": 1729267061375
        }
      },
      "LQ6xqThd9sB75yziJ29q4": {
        "id": "LQ6xqThd9sB75yziJ29q4",
        "name": "ADMREL_ROLUSU",
        "comment": "",
        "columnIds": [
          "8-0oERPNzY8WVxk0RaI4j",
          "bNUV89eVjQaxI5Xj33ik-",
          "-MGcSurd8FjR7kvvOnydf"
        ],
        "seqColumnIds": [
          "8-0oERPNzY8WVxk0RaI4j",
          "bNUV89eVjQaxI5Xj33ik-",
          "EcFzv1jwP6GmVaPSe0h08",
          "-MGcSurd8FjR7kvvOnydf"
        ],
        "ui": {
          "x": 515.5531,
          "y": 900.7208,
          "zIndex": 24,
          "widthName": 97,
          "widthComment": 60,
          "color": ""
        },
        "meta": {
          "updateAt": 1730226623529,
          "createAt": 1729267148685
        }
      },
      "dPNIQ1drtSQcs5zYD5J6k": {
        "id": "dPNIQ1drtSQcs5zYD5J6k",
        "name": "ADMCNF_ROLES",
        "comment": "",
        "columnIds": [
          "UTWwgy9OiObGfYdOBK8jG",
          "nXNpNPFYx3_H1hB0Bz6iA",
          "E6LG2TtoI7PNjHeu54vl4"
        ],
        "seqColumnIds": [
          "UTWwgy9OiObGfYdOBK8jG",
          "nXNpNPFYx3_H1hB0Bz6iA",
          "E6LG2TtoI7PNjHeu54vl4"
        ],
        "ui": {
          "x": 509.4442,
          "y": 1320.9028,
          "zIndex": 34,
          "widthName": 90,
          "widthComment": 60,
          "color": ""
        },
        "meta": {
          "updateAt": 1730226571595,
          "createAt": 1729267312802
        }
      },
      "AblPsS5f9kFkxgnlNHuR4": {
        "id": "AblPsS5f9kFkxgnlNHuR4",
        "name": "ADMCAT_ACCIONES",
        "comment": "",
        "columnIds": [
          "nWRI1Fpaj_fn8Uwt67FQ8",
          "4mI15uUm-aUd3cIgozEhM",
          "eMpdEQ5KRJy8xPiDJ0WL0"
        ],
        "seqColumnIds": [
          "0aqdazY0rmgx7ASNWK84R",
          "nWRI1Fpaj_fn8Uwt67FQ8",
          "4mI15uUm-aUd3cIgozEhM",
          "eMpdEQ5KRJy8xPiDJ0WL0"
        ],
        "ui": {
          "x": 1169.01,
          "y": 888.2105,
          "zIndex": 52,
          "widthName": 110,
          "widthComment": 60,
          "color": ""
        },
        "meta": {
          "updateAt": 1730226177913,
          "createAt": 1729267594938
        }
      },
      "h5wO3PYGvf-QvEnUodwWD": {
        "id": "h5wO3PYGvf-QvEnUodwWD",
        "name": "ADMCAT_FUNCIONALIDADES",
        "comment": "",
        "columnIds": [
          "SQD28Msh3wGhA4fl0rNt_",
          "NTClLTXslrBVfs_hfnIwW",
          "LElIDzWJvLxWLpr_NWUMk",
          "9Lwd3sYJLSWsJpqhPY778"
        ],
        "seqColumnIds": [
          "H9E7zl7N7p9CNQrdVxmuU",
          "SQD28Msh3wGhA4fl0rNt_",
          "NTClLTXslrBVfs_hfnIwW",
          "3GXytbJ6ph_zehmFc5wx4",
          "LElIDzWJvLxWLpr_NWUMk",
          "9Lwd3sYJLSWsJpqhPY778",
          "-VXeuBq5RV4Vr134u3OQF"
        ],
        "ui": {
          "x": 2323.28,
          "y": 1289.3155,
          "zIndex": 57,
          "widthName": 160,
          "widthComment": 60,
          "color": ""
        },
        "meta": {
          "updateAt": 1730226197626,
          "createAt": 1729267603794
        }
      },
      "MZzQgWsKLlCjdaTvkv_5n": {
        "id": "MZzQgWsKLlCjdaTvkv_5n",
        "name": "ADMCAT_MODULO",
        "comment": "",
        "columnIds": [
          "TUg0Y3dWTCk29vCSmQFfS",
          "vlOwlrHNzAnlBEOfDUz3H",
          "eJbChfbITolz3Q1Hc8c1f",
          "OPEWIraV2yNTD6syGf2fE"
        ],
        "seqColumnIds": [
          "TUg0Y3dWTCk29vCSmQFfS",
          "vlOwlrHNzAnlBEOfDUz3H",
          "eJbChfbITolz3Q1Hc8c1f",
          "OPEWIraV2yNTD6syGf2fE"
        ],
        "ui": {
          "x": 2893.1855,
          "y": 1289.0885,
          "zIndex": 63,
          "widthName": 105,
          "widthComment": 60,
          "color": ""
        },
        "meta": {
          "updateAt": 1730226275528,
          "createAt": 1729267633855
        }
      },
      "PZABfmy4YQI78cd8GmzKI": {
        "id": "PZABfmy4YQI78cd8GmzKI",
        "name": "ADMREL_ACCFUN",
        "comment": "",
        "columnIds": [
          "Lzi4Dove5noE9Hye7q6st",
          "pUcs85xaL2-tF5Mlo2jyS"
        ],
        "seqColumnIds": [
          "nyOI0O3XLXTc96FCJCwZx",
          "9HuYrSze1wzzUN69Bn73Y",
          "Lzi4Dove5noE9Hye7q6st",
          "pUcs85xaL2-tF5Mlo2jyS"
        ],
        "ui": {
          "x": 1813.16,
          "y": 899.9377,
          "zIndex": 88,
          "widthName": 98,
          "widthComment": 60,
          "color": ""
        },
        "meta": {
          "updateAt": 1730226501922,
          "createAt": 1729267928705
        }
      },
      "ljgpQ-ut5b5LoN7vA-yQR": {
        "id": "ljgpQ-ut5b5LoN7vA-yQR",
        "name": "ADMREL_ACCFUNROL",
        "comment": "",
        "columnIds": [
          "gKaUAx6CC5TvsVWTKbYWn",
          "Oq66Upuo2UT2nBchDN9dJ",
          "xISgtW271xZI0_lnOe2DX",
          "-Jjf8jIkfxvKlw_mz9Ypw"
        ],
        "seqColumnIds": [
          "ikq-YP-qxaD-XxkVSaS1Q",
          "gKaUAx6CC5TvsVWTKbYWn",
          "Oq66Upuo2UT2nBchDN9dJ",
          "xISgtW271xZI0_lnOe2DX",
          "-Jjf8jIkfxvKlw_mz9Ypw"
        ],
        "ui": {
          "x": 1168.3029,
          "y": 1308.4506,
          "zIndex": 117,
          "widthName": 120,
          "widthComment": 60,
          "color": ""
        },
        "meta": {
          "updateAt": 1730226534896,
          "createAt": 1729268053900
        }
      },
      "nI60JygSC7yhleBHLTc_E": {
        "id": "nI60JygSC7yhleBHLTc_E",
        "name": "LOGREG_ENTIDADES",
        "comment": "",
        "columnIds": [
          "UB-KSMm4ddqKQ3X8TJj4p",
          "TO8Ug-uteTAYxIETYvl7_",
          "3cHZ9bpPHqcnxHb64mxd_",
          "AW8gWTXUejkiMFlAMrx5z",
          "YB-p2ZOJRiBcH1ql7eTuq",
          "8Xp6kiOqRt7VACes79SwC",
          "cvObatuMh3ENwEZnzgXWh",
          "-9YTMjEZIjexsprzBUQXC",
          "Bjzuj4fKIRR40wUjw8wcA",
          "89AOnOlBrzl1U52eLgSDI",
          "fer33Y7k_muAm2eOPpxdg"
        ],
        "seqColumnIds": [
          "UB-KSMm4ddqKQ3X8TJj4p",
          "TO8Ug-uteTAYxIETYvl7_",
          "3cHZ9bpPHqcnxHb64mxd_",
          "AW8gWTXUejkiMFlAMrx5z",
          "YB-p2ZOJRiBcH1ql7eTuq",
          "8Xp6kiOqRt7VACes79SwC",
          "cvObatuMh3ENwEZnzgXWh",
          "-9YTMjEZIjexsprzBUQXC",
          "Bjzuj4fKIRR40wUjw8wcA",
          "89AOnOlBrzl1U52eLgSDI",
          "fer33Y7k_muAm2eOPpxdg"
        ],
        "ui": {
          "x": 1026.8293,
          "y": 12.1953,
          "zIndex": 268,
          "widthName": 112,
          "widthComment": 60,
          "color": ""
        },
        "meta": {
          "updateAt": 1730229140288,
          "createAt": 1730228316304
        }
      }
    },
    "tableColumnEntities": {
      "hYEQ0o8cybYRYyJaygNWA": {
        "id": "hYEQ0o8cybYRYyJaygNWA",
        "tableId": "IVFL0tVOqoKbhTHys2c68",
        "name": "",
        "comment": "",
        "dataType": "",
        "default": "",
        "options": 0,
        "ui": {
          "keys": 0,
          "widthName": 60,
          "widthComment": 60,
          "widthDataType": 60,
          "widthDefault": 60
        },
        "meta": {
          "updateAt": 1729267051020,
          "createAt": 1729267051020
        }
      },
      "a2Ylt0NMtvJaB4V9I-bzp": {
        "id": "a2Ylt0NMtvJaB4V9I-bzp",
        "tableId": "IVFL0tVOqoKbhTHys2c68",
        "name": "IDENTIDAD",
        "comment": "",
        "dataType": "INT",
        "default": "",
        "options": 10,
        "ui": {
          "keys": 1,
          "widthName": 62,
          "widthComment": 60,
          "widthDataType": 60,
          "widthDefault": 60
        },
        "meta": {
          "updateAt": 1729703978809,
          "createAt": 1729267112726
        }
      },
      "AeuHd-sdgcfEAIFrLRtzc": {
        "id": "AeuHd-sdgcfEAIFrLRtzc",
        "tableId": "ic8qI8cXoM7FoDHA6eZO2",
        "name": "",
        "comment": "",
        "dataType": "",
        "default": "",
        "options": 0,
        "ui": {
          "keys": 0,
          "widthName": 60,
          "widthComment": 60,
          "widthDataType": 60,
          "widthDefault": 60
        },
        "meta": {
          "updateAt": 1729267117057,
          "createAt": 1729267117057
        }
      },
      "UTWwgy9OiObGfYdOBK8jG": {
        "id": "UTWwgy9OiObGfYdOBK8jG",
        "tableId": "dPNIQ1drtSQcs5zYD5J6k",
        "name": "IDROL",
        "comment": "",
        "dataType": "",
        "default": "",
        "options": 10,
        "ui": {
          "keys": 1,
          "widthName": 60,
          "widthComment": 60,
          "widthDataType": 60,
          "widthDefault": 60
        },
        "meta": {
          "updateAt": 1729704984313,
          "createAt": 1729267329517
        }
      },
      "8-0oERPNzY8WVxk0RaI4j": {
        "id": "8-0oERPNzY8WVxk0RaI4j",
        "tableId": "LQ6xqThd9sB75yziJ29q4",
        "name": "IDROL",
        "comment": "",
        "dataType": "",
        "default": "",
        "options": 8,
        "ui": {
          "keys": 2,
          "widthName": 60,
          "widthComment": 60,
          "widthDataType": 60,
          "widthDefault": 60
        },
        "meta": {
          "updateAt": 1729707168804,
          "createAt": 1729267330995
        }
      },
      "9TMxcuD0BUhpN_NJtKaI_": {
        "id": "9TMxcuD0BUhpN_NJtKaI_",
        "tableId": "ic8qI8cXoM7FoDHA6eZO2",
        "name": "IDENTIDAD",
        "comment": "",
        "dataType": "INT",
        "default": "",
        "options": 8,
        "ui": {
          "keys": 2,
          "widthName": 62,
          "widthComment": 60,
          "widthDataType": 60,
          "widthDefault": 60
        },
        "meta": {
          "updateAt": 1729707146996,
          "createAt": 1729267535222
        }
      },
      "0aqdazY0rmgx7ASNWK84R": {
        "id": "0aqdazY0rmgx7ASNWK84R",
        "tableId": "AblPsS5f9kFkxgnlNHuR4",
        "name": "",
        "comment": "",
        "dataType": "",
        "default": "",
        "options": 0,
        "ui": {
          "keys": 0,
          "widthName": 60,
          "widthComment": 60,
          "widthDataType": 60,
          "widthDefault": 60
        },
        "meta": {
          "updateAt": 1729267600595,
          "createAt": 1729267600595
        }
      },
      "vlOwlrHNzAnlBEOfDUz3H": {
        "id": "vlOwlrHNzAnlBEOfDUz3H",
        "tableId": "MZzQgWsKLlCjdaTvkv_5n",
        "name": "IDMODULO",
        "comment": "",
        "dataType": "INT",
        "default": "",
        "options": 10,
        "ui": {
          "keys": 1,
          "widthName": 64,
          "widthComment": 60,
          "widthDataType": 60,
          "widthDefault": 60
        },
        "meta": {
          "updateAt": 1729704372591,
          "createAt": 1729267683603
        }
      },
      "TUg0Y3dWTCk29vCSmQFfS": {
        "id": "TUg0Y3dWTCk29vCSmQFfS",
        "tableId": "MZzQgWsKLlCjdaTvkv_5n",
        "name": "FKMODULO",
        "comment": "",
        "dataType": "INT",
        "default": "",
        "options": 8,
        "ui": {
          "keys": 2,
          "widthName": 66,
          "widthComment": 60,
          "widthDataType": 60,
          "widthDefault": 60
        },
        "meta": {
          "updateAt": 1729705418082,
          "createAt": 1729267685617
        }
      },
      "H9E7zl7N7p9CNQrdVxmuU": {
        "id": "H9E7zl7N7p9CNQrdVxmuU",
        "tableId": "h5wO3PYGvf-QvEnUodwWD",
        "name": "",
        "comment": "",
        "dataType": "",
        "default": "",
        "options": 0,
        "ui": {
          "keys": 0,
          "widthName": 60,
          "widthComment": 60,
          "widthDataType": 60,
          "widthDefault": 60
        },
        "meta": {
          "updateAt": 1729267715358,
          "createAt": 1729267715358
        }
      },
      "SQD28Msh3wGhA4fl0rNt_": {
        "id": "SQD28Msh3wGhA4fl0rNt_",
        "tableId": "h5wO3PYGvf-QvEnUodwWD",
        "name": "IDMODULO",
        "comment": "",
        "dataType": "INT",
        "default": "",
        "options": 8,
        "ui": {
          "keys": 2,
          "widthName": 64,
          "widthComment": 60,
          "widthDataType": 60,
          "widthDefault": 60
        },
        "meta": {
          "updateAt": 1729707300109,
          "createAt": 1729267725921
        }
      },
      "nyOI0O3XLXTc96FCJCwZx": {
        "id": "nyOI0O3XLXTc96FCJCwZx",
        "tableId": "PZABfmy4YQI78cd8GmzKI",
        "name": "",
        "comment": "",
        "dataType": "",
        "default": "",
        "options": 0,
        "ui": {
          "keys": 0,
          "widthName": 60,
          "widthComment": 60,
          "widthDataType": 60,
          "widthDefault": 60
        },
        "meta": {
          "updateAt": 1729267936903,
          "createAt": 1729267936903
        }
      },
      "NTClLTXslrBVfs_hfnIwW": {
        "id": "NTClLTXslrBVfs_hfnIwW",
        "tableId": "h5wO3PYGvf-QvEnUodwWD",
        "name": "IDFUNCIONALIDAD",
        "comment": "",
        "dataType": "INT",
        "default": "",
        "options": 10,
        "ui": {
          "keys": 1,
          "widthName": 106,
          "widthComment": 60,
          "widthDataType": 60,
          "widthDefault": 60
        },
        "meta": {
          "updateAt": 1729704022816,
          "createAt": 1729267948994
        }
      },
      "pUcs85xaL2-tF5Mlo2jyS": {
        "id": "pUcs85xaL2-tF5Mlo2jyS",
        "tableId": "PZABfmy4YQI78cd8GmzKI",
        "name": "IDFUNCIONALIDAD",
        "comment": "",
        "dataType": "INT",
        "default": "",
        "options": 8,
        "ui": {
          "keys": 2,
          "widthName": 106,
          "widthComment": 60,
          "widthDataType": 60,
          "widthDefault": 60
        },
        "meta": {
          "updateAt": 1729707278537,
          "createAt": 1729267950802
        }
      },
      "nWRI1Fpaj_fn8Uwt67FQ8": {
        "id": "nWRI1Fpaj_fn8Uwt67FQ8",
        "tableId": "AblPsS5f9kFkxgnlNHuR4",
        "name": "IDACCION",
        "comment": "",
        "dataType": "INT",
        "default": "",
        "options": 10,
        "ui": {
          "keys": 1,
          "widthName": 60,
          "widthComment": 60,
          "widthDataType": 60,
          "widthDefault": 60
        },
        "meta": {
          "updateAt": 1729704502521,
          "createAt": 1729268007706
        }
      },
      "Lzi4Dove5noE9Hye7q6st": {
        "id": "Lzi4Dove5noE9Hye7q6st",
        "tableId": "PZABfmy4YQI78cd8GmzKI",
        "name": "IDACCION",
        "comment": "",
        "dataType": "INT",
        "default": "",
        "options": 8,
        "ui": {
          "keys": 2,
          "widthName": 60,
          "widthComment": 60,
          "widthDataType": 60,
          "widthDefault": 60
        },
        "meta": {
          "updateAt": 1729707266405,
          "createAt": 1729268009132
        }
      },
      "ikq-YP-qxaD-XxkVSaS1Q": {
        "id": "ikq-YP-qxaD-XxkVSaS1Q",
        "tableId": "ljgpQ-ut5b5LoN7vA-yQR",
        "name": "",
        "comment": "",
        "dataType": "",
        "default": "",
        "options": 0,
        "ui": {
          "keys": 0,
          "widthName": 60,
          "widthComment": 60,
          "widthDataType": 60,
          "widthDefault": 60
        },
        "meta": {
          "updateAt": 1729268066336,
          "createAt": 1729268066336
        }
      },
      "Oq66Upuo2UT2nBchDN9dJ": {
        "id": "Oq66Upuo2UT2nBchDN9dJ",
        "tableId": "ljgpQ-ut5b5LoN7vA-yQR",
        "name": "IDFUNCIONALIDAD",
        "comment": "",
        "dataType": "INT",
        "default": "",
        "options": 8,
        "ui": {
          "keys": 2,
          "widthName": 106,
          "widthComment": 60,
          "widthDataType": 60,
          "widthDefault": 60
        },
        "meta": {
          "updateAt": 1729707230286,
          "createAt": 1729268091806
        }
      },
      "gKaUAx6CC5TvsVWTKbYWn": {
        "id": "gKaUAx6CC5TvsVWTKbYWn",
        "tableId": "ljgpQ-ut5b5LoN7vA-yQR",
        "name": "IDACCION",
        "comment": "",
        "dataType": "INT",
        "default": "",
        "options": 8,
        "ui": {
          "keys": 2,
          "widthName": 60,
          "widthComment": 60,
          "widthDataType": 60,
          "widthDefault": 60
        },
        "meta": {
          "updateAt": 1729707200565,
          "createAt": 1729268139593
        }
      },
      "xISgtW271xZI0_lnOe2DX": {
        "id": "xISgtW271xZI0_lnOe2DX",
        "tableId": "ljgpQ-ut5b5LoN7vA-yQR",
        "name": "IDROL",
        "comment": "",
        "dataType": "",
        "default": "",
        "options": 8,
        "ui": {
          "keys": 2,
          "widthName": 60,
          "widthComment": 60,
          "widthDataType": 60,
          "widthDefault": 60
        },
        "meta": {
          "updateAt": 1729707216393,
          "createAt": 1729268150379
        }
      },
      "9HuYrSze1wzzUN69Bn73Y": {
        "id": "9HuYrSze1wzzUN69Bn73Y",
        "tableId": "PZABfmy4YQI78cd8GmzKI",
        "name": "",
        "comment": "",
        "dataType": "",
        "default": "",
        "options": 8,
        "ui": {
          "keys": 0,
          "widthName": 60,
          "widthComment": 60,
          "widthDataType": 60,
          "widthDefault": 60
        },
        "meta": {
          "updateAt": 1729268170262,
          "createAt": 1729268170262
        }
      },
      "IYAlhJTjLLLQUrJ-S_j5A": {
        "id": "IYAlhJTjLLLQUrJ-S_j5A",
        "tableId": "ic8qI8cXoM7FoDHA6eZO2",
        "name": "IDUSUARIO",
        "comment": "",
        "dataType": "",
        "default": "",
        "options": 10,
        "ui": {
          "keys": 1,
          "widthName": 63,
          "widthComment": 60,
          "widthDataType": 60,
          "widthDefault": 60
        },
        "meta": {
          "updateAt": 1729706347498,
          "createAt": 1729269413823
        }
      },
      "bNUV89eVjQaxI5Xj33ik-": {
        "id": "bNUV89eVjQaxI5Xj33ik-",
        "tableId": "LQ6xqThd9sB75yziJ29q4",
        "name": "IDUSUARIO",
        "comment": "",
        "dataType": "",
        "default": "",
        "options": 8,
        "ui": {
          "keys": 2,
          "widthName": 63,
          "widthComment": 60,
          "widthDataType": 60,
          "widthDefault": 60
        },
        "meta": {
          "updateAt": 1729707107580,
          "createAt": 1729269415031
        }
      },
      "EcFzv1jwP6GmVaPSe0h08": {
        "id": "EcFzv1jwP6GmVaPSe0h08",
        "tableId": "LQ6xqThd9sB75yziJ29q4",
        "name": "",
        "comment": "",
        "dataType": "",
        "default": "",
        "options": 8,
        "ui": {
          "keys": 0,
          "widthName": 60,
          "widthComment": 60,
          "widthDataType": 60,
          "widthDefault": 60
        },
        "meta": {
          "updateAt": 1729698703804,
          "createAt": 1729698703803
        }
      },
      "-MGcSurd8FjR7kvvOnydf": {
        "id": "-MGcSurd8FjR7kvvOnydf",
        "tableId": "LQ6xqThd9sB75yziJ29q4",
        "name": "IDROLUSUARIO",
        "comment": "",
        "dataType": "INT",
        "default": "",
        "options": 10,
        "ui": {
          "keys": 1,
          "widthName": 85,
          "widthComment": 60,
          "widthDataType": 60,
          "widthDefault": 60
        },
        "meta": {
          "updateAt": 1729704957658,
          "createAt": 1729698720212
        }
      },
      "Xq9_PHOLJjaFhQzoVvFzM": {
        "id": "Xq9_PHOLJjaFhQzoVvFzM",
        "tableId": "ic8qI8cXoM7FoDHA6eZO2",
        "name": "IDROLUSUARIO",
        "comment": "",
        "dataType": "INT",
        "default": "",
        "options": 8,
        "ui": {
          "keys": 2,
          "widthName": 85,
          "widthComment": 60,
          "widthDataType": 60,
          "widthDefault": 60
        },
        "meta": {
          "updateAt": 1729707617864,
          "createAt": 1729698722856
        }
      },
      "5kJQPXpyhUS1doRa_BEKv": {
        "id": "5kJQPXpyhUS1doRa_BEKv",
        "tableId": "IVFL0tVOqoKbhTHys2c68",
        "name": "IDENTIDAD",
        "comment": "",
        "dataType": "INT",
        "default": "",
        "options": 10,
        "ui": {
          "keys": 1,
          "widthName": 62,
          "widthComment": 60,
          "widthDataType": 60,
          "widthDefault": 60
        },
        "meta": {
          "updateAt": 1729703094772,
          "createAt": 1729701799713
        }
      },
      "aJTMV8sFMZRYyeR5iz8Qi": {
        "id": "aJTMV8sFMZRYyeR5iz8Qi",
        "tableId": "IVFL0tVOqoKbhTHys2c68",
        "name": "ENTNOMBRE",
        "comment": "",
        "dataType": "VARCHAR",
        "default": "",
        "options": 0,
        "ui": {
          "keys": 0,
          "widthName": 72,
          "widthComment": 60,
          "widthDataType": 60,
          "widthDefault": 60
        },
        "meta": {
          "updateAt": 1729702314890,
          "createAt": 1729701872586
        }
      },
      "DX0OA5goKXQJeX7f-SeRg": {
        "id": "DX0OA5goKXQJeX7f-SeRg",
        "tableId": "IVFL0tVOqoKbhTHys2c68",
        "name": "ENTDESCRIPCION",
        "comment": "",
        "dataType": "VARCHAR",
        "default": "",
        "options": 0,
        "ui": {
          "keys": 0,
          "widthName": 97,
          "widthComment": 60,
          "widthDataType": 60,
          "widthDefault": 60
        },
        "meta": {
          "updateAt": 1729702355669,
          "createAt": 1729701883463
        }
      },
      "PuRQlQEBGGJI17X9vnYBH": {
        "id": "PuRQlQEBGGJI17X9vnYBH",
        "tableId": "IVFL0tVOqoKbhTHys2c68",
        "name": "ENTFECHA",
        "comment": "",
        "dataType": "DATE",
        "default": "",
        "options": 0,
        "ui": {
          "keys": 0,
          "widthName": 60,
          "widthComment": 60,
          "widthDataType": 60,
          "widthDefault": 60
        },
        "meta": {
          "updateAt": 1729702492890,
          "createAt": 1729701897944
        }
      },
      "EDrVmf-w0ipe4MZ5NoAJF": {
        "id": "EDrVmf-w0ipe4MZ5NoAJF",
        "tableId": "IVFL0tVOqoKbhTHys2c68",
        "name": "ENTESTADO",
        "comment": "",
        "dataType": "BOOLEAN",
        "default": "",
        "options": 0,
        "ui": {
          "keys": 0,
          "widthName": 66,
          "widthComment": 60,
          "widthDataType": 60,
          "widthDefault": 60
        },
        "meta": {
          "updateAt": 1729702413039,
          "createAt": 1729701903861
        }
      },
      "EQwX-3e3hikkLxuLDb8i3": {
        "id": "EQwX-3e3hikkLxuLDb8i3",
        "tableId": "ic8qI8cXoM7FoDHA6eZO2",
        "name": "IDUSUARIO",
        "comment": "",
        "dataType": "INT",
        "default": "",
        "options": 10,
        "ui": {
          "keys": 1,
          "widthName": 63,
          "widthComment": 60,
          "widthDataType": 60,
          "widthDefault": 60
        },
        "meta": {
          "updateAt": 1729703163032,
          "createAt": 1729702536587
        }
      },
      "9-xFfkpsAbXJQd_HI7g2m": {
        "id": "9-xFfkpsAbXJQd_HI7g2m",
        "tableId": "ic8qI8cXoM7FoDHA6eZO2",
        "name": "USUNOMBRE",
        "comment": "",
        "dataType": "VARCHAR",
        "default": "",
        "options": 0,
        "ui": {
          "keys": 0,
          "widthName": 74,
          "widthComment": 60,
          "widthDataType": 60,
          "widthDefault": 60
        },
        "meta": {
          "updateAt": 1729703159058,
          "createAt": 1729702701859
        }
      },
      "zXKxytADtc7w7wjwUQ4Bx": {
        "id": "zXKxytADtc7w7wjwUQ4Bx",
        "tableId": "ic8qI8cXoM7FoDHA6eZO2",
        "name": "USUCORREO",
        "comment": "",
        "dataType": "VARCHAR",
        "default": "",
        "options": 0,
        "ui": {
          "keys": 0,
          "widthName": 70,
          "widthComment": 60,
          "widthDataType": 60,
          "widthDefault": 60
        },
        "meta": {
          "updateAt": 1729703167588,
          "createAt": 1729702713017
        }
      },
      "lVJ7BHwsMrEpcnmh782vG": {
        "id": "lVJ7BHwsMrEpcnmh782vG",
        "tableId": "ic8qI8cXoM7FoDHA6eZO2",
        "name": "USUCONTRASENA",
        "comment": "",
        "dataType": "VARCHAR",
        "default": "",
        "options": 0,
        "ui": {
          "keys": 0,
          "widthName": 100,
          "widthComment": 60,
          "widthDataType": 60,
          "widthDefault": 60
        },
        "meta": {
          "updateAt": 1729703169640,
          "createAt": 1729702721907
        }
      },
      "FPsmcP2g66A0veDbreDWP": {
        "id": "FPsmcP2g66A0veDbreDWP",
        "tableId": "ic8qI8cXoM7FoDHA6eZO2",
        "name": "USUFECHA",
        "comment": "",
        "dataType": "DATE",
        "default": "",
        "options": 0,
        "ui": {
          "keys": 0,
          "widthName": 60,
          "widthComment": 60,
          "widthDataType": 60,
          "widthDefault": 60
        },
        "meta": {
          "updateAt": 1729703172538,
          "createAt": 1729702737758
        }
      },
      "yfE7Ssgx-mKwZ3ANDU-mr": {
        "id": "yfE7Ssgx-mKwZ3ANDU-mr",
        "tableId": "ic8qI8cXoM7FoDHA6eZO2",
        "name": "USUESTADO",
        "comment": "",
        "dataType": "VARCHAR",
        "default": "",
        "options": 0,
        "ui": {
          "keys": 0,
          "widthName": 68,
          "widthComment": 60,
          "widthDataType": 60,
          "widthDefault": 60
        },
        "meta": {
          "updateAt": 1729703176176,
          "createAt": 1729702748929
        }
      },
      "3GXytbJ6ph_zehmFc5wx4": {
        "id": "3GXytbJ6ph_zehmFc5wx4",
        "tableId": "h5wO3PYGvf-QvEnUodwWD",
        "name": "id_funcionalidad",
        "comment": "",
        "dataType": "",
        "default": "",
        "options": 0,
        "ui": {
          "keys": 0,
          "widthName": 89,
          "widthComment": 60,
          "widthDataType": 60,
          "widthDefault": 60
        },
        "meta": {
          "updateAt": 1729703763336,
          "createAt": 1729703755550
        }
      },
      "LElIDzWJvLxWLpr_NWUMk": {
        "id": "LElIDzWJvLxWLpr_NWUMk",
        "tableId": "h5wO3PYGvf-QvEnUodwWD",
        "name": "FUNNOMBRE",
        "comment": "",
        "dataType": "VARCHAR",
        "default": "",
        "options": 0,
        "ui": {
          "keys": 0,
          "widthName": 74,
          "widthComment": 60,
          "widthDataType": 60,
          "widthDefault": 60
        },
        "meta": {
          "updateAt": 1729704513349,
          "createAt": 1729703764994
        }
      },
      "9Lwd3sYJLSWsJpqhPY778": {
        "id": "9Lwd3sYJLSWsJpqhPY778",
        "tableId": "h5wO3PYGvf-QvEnUodwWD",
        "name": "FUNDESCRIPCION",
        "comment": "",
        "dataType": "VARCHAR",
        "default": "",
        "options": 0,
        "ui": {
          "keys": 0,
          "widthName": 99,
          "widthComment": 60,
          "widthDataType": 60,
          "widthDefault": 60
        },
        "meta": {
          "updateAt": 1729704515066,
          "createAt": 1729703773439
        }
      },
      "-VXeuBq5RV4Vr134u3OQF": {
        "id": "-VXeuBq5RV4Vr134u3OQF",
        "tableId": "h5wO3PYGvf-QvEnUodwWD",
        "name": "",
        "comment": "",
        "dataType": "",
        "default": "",
        "options": 0,
        "ui": {
          "keys": 0,
          "widthName": 60,
          "widthComment": 60,
          "widthDataType": 60,
          "widthDefault": 60
        },
        "meta": {
          "updateAt": 1729703782576,
          "createAt": 1729703782576
        }
      },
      "eJbChfbITolz3Q1Hc8c1f": {
        "id": "eJbChfbITolz3Q1Hc8c1f",
        "tableId": "MZzQgWsKLlCjdaTvkv_5n",
        "name": "MODNOMBRE",
        "comment": "",
        "dataType": "VARCHAR",
        "default": "",
        "options": 0,
        "ui": {
          "keys": 0,
          "widthName": 79,
          "widthComment": 60,
          "widthDataType": 60,
          "widthDefault": 60
        },
        "meta": {
          "updateAt": 1729704312234,
          "createAt": 1729704244647
        }
      },
      "OPEWIraV2yNTD6syGf2fE": {
        "id": "OPEWIraV2yNTD6syGf2fE",
        "tableId": "MZzQgWsKLlCjdaTvkv_5n",
        "name": "MODDESCRIPCION",
        "comment": "",
        "dataType": "VARCHAR",
        "default": "",
        "options": 0,
        "ui": {
          "keys": 0,
          "widthName": 104,
          "widthComment": 60,
          "widthDataType": 60,
          "widthDefault": 60
        },
        "meta": {
          "updateAt": 1729704314859,
          "createAt": 1729704251528
        }
      },
      "4mI15uUm-aUd3cIgozEhM": {
        "id": "4mI15uUm-aUd3cIgozEhM",
        "tableId": "AblPsS5f9kFkxgnlNHuR4",
        "name": "ACCNOMBRE",
        "comment": "",
        "dataType": "VARCHAR",
        "default": "",
        "options": 0,
        "ui": {
          "keys": 0,
          "widthName": 73,
          "widthComment": 60,
          "widthDataType": 60,
          "widthDefault": 60
        },
        "meta": {
          "updateAt": 1729704505759,
          "createAt": 1729704393260
        }
      },
      "eMpdEQ5KRJy8xPiDJ0WL0": {
        "id": "eMpdEQ5KRJy8xPiDJ0WL0",
        "tableId": "AblPsS5f9kFkxgnlNHuR4",
        "name": "ACCDESCRIPCION",
        "comment": "",
        "dataType": "VARCHAR",
        "default": "",
        "options": 0,
        "ui": {
          "keys": 0,
          "widthName": 98,
          "widthComment": 60,
          "widthDataType": 60,
          "widthDefault": 60
        },
        "meta": {
          "updateAt": 1729704507536,
          "createAt": 1729704393955
        }
      },
      "nXNpNPFYx3_H1hB0Bz6iA": {
        "id": "nXNpNPFYx3_H1hB0Bz6iA",
        "tableId": "dPNIQ1drtSQcs5zYD5J6k",
        "name": "ROLNOMBRE",
        "comment": "",
        "dataType": "",
        "default": "",
        "options": 0,
        "ui": {
          "keys": 0,
          "widthName": 73,
          "widthComment": 60,
          "widthDataType": 60,
          "widthDefault": 60
        },
        "meta": {
          "updateAt": 1729704994632,
          "createAt": 1729704944590
        }
      },
      "E6LG2TtoI7PNjHeu54vl4": {
        "id": "E6LG2TtoI7PNjHeu54vl4",
        "tableId": "dPNIQ1drtSQcs5zYD5J6k",
        "name": "ROLDESCRIPCION",
        "comment": "",
        "dataType": "",
        "default": "",
        "options": 0,
        "ui": {
          "keys": 0,
          "widthName": 98,
          "widthComment": 60,
          "widthDataType": 60,
          "widthDefault": 60
        },
        "meta": {
          "updateAt": 1729705005202,
          "createAt": 1729704945276
        }
      },
      "-Jjf8jIkfxvKlw_mz9Ypw": {
        "id": "-Jjf8jIkfxvKlw_mz9Ypw",
        "tableId": "ljgpQ-ut5b5LoN7vA-yQR",
        "name": "ROLFUNPERMISOS",
        "comment": "",
        "dataType": "BOOLEAN",
        "default": "",
        "options": 0,
        "ui": {
          "keys": 0,
          "widthName": 103,
          "widthComment": 60,
          "widthDataType": 60,
          "widthDefault": 60
        },
        "meta": {
          "updateAt": 1729705163064,
          "createAt": 1729705144075
        }
      },
      "TO8Ug-uteTAYxIETYvl7_": {
        "id": "TO8Ug-uteTAYxIETYvl7_",
        "tableId": "nI60JygSC7yhleBHLTc_E",
        "name": "LOGREG_IDENTIDADCREA",
        "comment": "",
        "dataType": "INT",
        "default": "",
        "options": 0,
        "ui": {
          "keys": 0,
          "widthName": 140,
          "widthComment": 60,
          "widthDataType": 60,
          "widthDefault": 60
        },
        "meta": {
          "updateAt": 1730228460139,
          "createAt": 1730228367519
        }
      },
      "3cHZ9bpPHqcnxHb64mxd_": {
        "id": "3cHZ9bpPHqcnxHb64mxd_",
        "tableId": "nI60JygSC7yhleBHLTc_E",
        "name": "LOGREG_IDENTIDADMODIFICA",
        "comment": "",
        "dataType": "INT",
        "default": "",
        "options": 0,
        "ui": {
          "keys": 0,
          "widthName": 167,
          "widthComment": 60,
          "widthDataType": 60,
          "widthDefault": 60
        },
        "meta": {
          "updateAt": 1730228520136,
          "createAt": 1730228444326
        }
      },
      "AW8gWTXUejkiMFlAMrx5z": {
        "id": "AW8gWTXUejkiMFlAMrx5z",
        "tableId": "nI60JygSC7yhleBHLTc_E",
        "name": "LOGREG_ENTNOMBRECREA",
        "comment": "",
        "dataType": "VARCHAR",
        "default": "",
        "options": 0,
        "ui": {
          "keys": 0,
          "widthName": 150,
          "widthComment": 60,
          "widthDataType": 60,
          "widthDefault": 60
        },
        "meta": {
          "updateAt": 1730228548838,
          "createAt": 1730228468734
        }
      },
      "YB-p2ZOJRiBcH1ql7eTuq": {
        "id": "YB-p2ZOJRiBcH1ql7eTuq",
        "tableId": "nI60JygSC7yhleBHLTc_E",
        "name": "LOGREG_ENTNOMBREMODIFICA",
        "comment": "",
        "dataType": "VARCHAR",
        "default": "",
        "options": 0,
        "ui": {
          "keys": 0,
          "widthName": 177,
          "widthComment": 60,
          "widthDataType": 60,
          "widthDefault": 60
        },
        "meta": {
          "updateAt": 1730228853244,
          "createAt": 1730228555838
        }
      },
      "UB-KSMm4ddqKQ3X8TJj4p": {
        "id": "UB-KSMm4ddqKQ3X8TJj4p",
        "tableId": "nI60JygSC7yhleBHLTc_E",
        "name": "IDENTIDAD",
        "comment": "",
        "dataType": "INT",
        "default": "",
        "options": 8,
        "ui": {
          "keys": 2,
          "widthName": 62,
          "widthComment": 60,
          "widthDataType": 60,
          "widthDefault": 60
        },
        "meta": {
          "updateAt": 1730228584192,
          "createAt": 1730228584192
        }
      },
      "8Xp6kiOqRt7VACes79SwC": {
        "id": "8Xp6kiOqRt7VACes79SwC",
        "tableId": "nI60JygSC7yhleBHLTc_E",
        "name": "LOGREG_ENTDESCRIPCIONCREA",
        "comment": "",
        "dataType": "VARCHAR",
        "default": "",
        "options": 0,
        "ui": {
          "keys": 0,
          "widthName": 175,
          "widthComment": 60,
          "widthDataType": 60,
          "widthDefault": 60
        },
        "meta": {
          "updateAt": 1730228846660,
          "createAt": 1730228605263
        }
      },
      "cvObatuMh3ENwEZnzgXWh": {
        "id": "cvObatuMh3ENwEZnzgXWh",
        "tableId": "nI60JygSC7yhleBHLTc_E",
        "name": "LOGREG_ENTDESCRIPCIONMODIFICA",
        "comment": "",
        "dataType": "VARCHAR",
        "default": "",
        "options": 0,
        "ui": {
          "keys": 0,
          "widthName": 202,
          "widthComment": 60,
          "widthDataType": 60,
          "widthDefault": 60
        },
        "meta": {
          "updateAt": 1730228843044,
          "createAt": 1730228643950
        }
      },
      "-9YTMjEZIjexsprzBUQXC": {
        "id": "-9YTMjEZIjexsprzBUQXC",
        "tableId": "nI60JygSC7yhleBHLTc_E",
        "name": "LOGREG_ENTFECHACREA",
        "comment": "",
        "dataType": "DATE",
        "default": "",
        "options": 0,
        "ui": {
          "keys": 0,
          "widthName": 136,
          "widthComment": 60,
          "widthDataType": 60,
          "widthDefault": 60
        },
        "meta": {
          "updateAt": 1730228832244,
          "createAt": 1730228704094
        }
      },
      "Bjzuj4fKIRR40wUjw8wcA": {
        "id": "Bjzuj4fKIRR40wUjw8wcA",
        "tableId": "nI60JygSC7yhleBHLTc_E",
        "name": "LOGREG_ENTFECHAMODIFICA",
        "comment": "",
        "dataType": "DATE",
        "default": "",
        "options": 0,
        "ui": {
          "keys": 0,
          "widthName": 164,
          "widthComment": 60,
          "widthDataType": 60,
          "widthDefault": 60
        },
        "meta": {
          "updateAt": 1730228838708,
          "createAt": 1730228734022
        }
      },
      "89AOnOlBrzl1U52eLgSDI": {
        "id": "89AOnOlBrzl1U52eLgSDI",
        "tableId": "nI60JygSC7yhleBHLTc_E",
        "name": "LOGREG_ENTESTADOCREA",
        "comment": "",
        "dataType": "BOOLEAN",
        "default": "",
        "options": 0,
        "ui": {
          "keys": 0,
          "widthName": 144,
          "widthComment": 60,
          "widthDataType": 60,
          "widthDefault": 60
        },
        "meta": {
          "updateAt": 1730228823756,
          "createAt": 1730228767782
        }
      },
      "fer33Y7k_muAm2eOPpxdg": {
        "id": "fer33Y7k_muAm2eOPpxdg",
        "tableId": "nI60JygSC7yhleBHLTc_E",
        "name": "LOGREG_ENTESTADOMODIFICA",
        "comment": "",
        "dataType": "BOOLEAN",
        "default": "",
        "options": 0,
        "ui": {
          "keys": 0,
          "widthName": 171,
          "widthComment": 60,
          "widthDataType": 60,
          "widthDefault": 60
        },
        "meta": {
          "updateAt": 1730228819460,
          "createAt": 1730228799629
        }
      }
    },
    "relationshipEntities": {
      "YtyghDogwvJ3JZTZeYz0H": {
        "id": "YtyghDogwvJ3JZTZeYz0H",
        "identification": false,
        "relationshipType": 16,
        "startRelationshipType": 2,
        "start": {
          "tableId": "dPNIQ1drtSQcs5zYD5J6k",
          "columnIds": [
            "UTWwgy9OiObGfYdOBK8jG"
          ],
          "x": 710.9442,
          "y": 1320.9028,
          "direction": 4
        },
        "end": {
          "tableId": "LQ6xqThd9sB75yziJ29q4",
          "columnIds": [
            "8-0oERPNzY8WVxk0RaI4j"
          ],
          "x": 710.5531,
          "y": 1028.7208,
          "direction": 8
        },
        "meta": {
          "updateAt": 1729267330996,
          "createAt": 1729267330996
        }
      },
      "GAlHyIcNQf2h2XprNrvaA": {
        "id": "GAlHyIcNQf2h2XprNrvaA",
        "identification": false,
        "relationshipType": 16,
        "startRelationshipType": 2,
        "start": {
          "tableId": "IVFL0tVOqoKbhTHys2c68",
          "columnIds": [
            "a2Ylt0NMtvJaB4V9I-bzp"
          ],
          "x": 712.5047999999999,
          "y": 261.8375,
          "direction": 8
        },
        "end": {
          "tableId": "ic8qI8cXoM7FoDHA6eZO2",
          "columnIds": [
            "9TMxcuD0BUhpN_NJtKaI_"
          ],
          "x": 710.8868,
          "y": 512.3357,
          "direction": 4
        },
        "meta": {
          "updateAt": 1729267535222,
          "createAt": 1729267535222
        }
      },
      "D-B-0aQD1qJvD6PizE4gx": {
        "id": "D-B-0aQD1qJvD6PizE4gx",
        "identification": false,
        "relationshipType": 8,
        "startRelationshipType": 2,
        "start": {
          "tableId": "MZzQgWsKLlCjdaTvkv_5n",
          "columnIds": [
            "vlOwlrHNzAnlBEOfDUz3H"
          ],
          "x": 3282.1855,
          "y": 1289.0885,
          "direction": 4
        },
        "end": {
          "tableId": "MZzQgWsKLlCjdaTvkv_5n",
          "columnIds": [
            "TUg0Y3dWTCk29vCSmQFfS"
          ],
          "x": 3302.1855,
          "y": 1309.0885,
          "direction": 2
        },
        "meta": {
          "updateAt": 1729267685618,
          "createAt": 1729267685618
        }
      },
      "Tw-aKEz6HEb7VwFdhW5wL": {
        "id": "Tw-aKEz6HEb7VwFdhW5wL",
        "identification": false,
        "relationshipType": 16,
        "startRelationshipType": 2,
        "start": {
          "tableId": "MZzQgWsKLlCjdaTvkv_5n",
          "columnIds": [
            "vlOwlrHNzAnlBEOfDUz3H"
          ],
          "x": 2893.1855,
          "y": 1365.0885,
          "direction": 1
        },
        "end": {
          "tableId": "h5wO3PYGvf-QvEnUodwWD",
          "columnIds": [
            "SQD28Msh3wGhA4fl0rNt_"
          ],
          "x": 2734.28,
          "y": 1365.3155,
          "direction": 2
        },
        "meta": {
          "updateAt": 1729267725921,
          "createAt": 1729267725921
        }
      },
      "qDMuPz6jUjd1DgoRAvS09": {
        "id": "qDMuPz6jUjd1DgoRAvS09",
        "identification": false,
        "relationshipType": 16,
        "startRelationshipType": 2,
        "start": {
          "tableId": "h5wO3PYGvf-QvEnUodwWD",
          "columnIds": [
            "NTClLTXslrBVfs_hfnIwW"
          ],
          "x": 2323.28,
          "y": 1327.3155,
          "direction": 1
        },
        "end": {
          "tableId": "PZABfmy4YQI78cd8GmzKI",
          "columnIds": [
            "pUcs85xaL2-tF5Mlo2jyS"
          ],
          "x": 2224.16,
          "y": 951.9377,
          "direction": 2
        },
        "meta": {
          "updateAt": 1729267950802,
          "createAt": 1729267950802
        }
      },
      "s3Q9bL-xfkaLt2zN3n2lD": {
        "id": "s3Q9bL-xfkaLt2zN3n2lD",
        "identification": false,
        "relationshipType": 16,
        "startRelationshipType": 2,
        "start": {
          "tableId": "AblPsS5f9kFkxgnlNHuR4",
          "columnIds": [
            "nWRI1Fpaj_fn8Uwt67FQ8"
          ],
          "x": 1572.01,
          "y": 952.2105,
          "direction": 2
        },
        "end": {
          "tableId": "PZABfmy4YQI78cd8GmzKI",
          "columnIds": [
            "Lzi4Dove5noE9Hye7q6st"
          ],
          "x": 1813.16,
          "y": 951.9377,
          "direction": 1
        },
        "meta": {
          "updateAt": 1729268009133,
          "createAt": 1729268009133
        }
      },
      "DNH8VKpvUj_2M8NjpsrM-": {
        "id": "DNH8VKpvUj_2M8NjpsrM-",
        "identification": false,
        "relationshipType": 16,
        "startRelationshipType": 2,
        "start": {
          "tableId": "h5wO3PYGvf-QvEnUodwWD",
          "columnIds": [
            "NTClLTXslrBVfs_hfnIwW"
          ],
          "x": 2323.28,
          "y": 1403.3155,
          "direction": 1
        },
        "end": {
          "tableId": "ljgpQ-ut5b5LoN7vA-yQR",
          "columnIds": [
            "Oq66Upuo2UT2nBchDN9dJ"
          ],
          "x": 1579.3029,
          "y": 1384.4506,
          "direction": 2
        },
        "meta": {
          "updateAt": 1729268091806,
          "createAt": 1729268091806
        }
      },
      "R1oOn_lrzmAo17E1Up3Ye": {
        "id": "R1oOn_lrzmAo17E1Up3Ye",
        "identification": false,
        "relationshipType": 16,
        "startRelationshipType": 2,
        "start": {
          "tableId": "AblPsS5f9kFkxgnlNHuR4",
          "columnIds": [
            "nWRI1Fpaj_fn8Uwt67FQ8"
          ],
          "x": 1370.51,
          "y": 1016.2105,
          "direction": 8
        },
        "end": {
          "tableId": "ljgpQ-ut5b5LoN7vA-yQR",
          "columnIds": [
            "gKaUAx6CC5TvsVWTKbYWn"
          ],
          "x": 1373.8029,
          "y": 1308.4506,
          "direction": 4
        },
        "meta": {
          "updateAt": 1729268139593,
          "createAt": 1729268139593
        }
      },
      "ojau24ldOTQOe6yNscmGW": {
        "id": "ojau24ldOTQOe6yNscmGW",
        "identification": false,
        "relationshipType": 16,
        "startRelationshipType": 2,
        "start": {
          "tableId": "dPNIQ1drtSQcs5zYD5J6k",
          "columnIds": [
            "UTWwgy9OiObGfYdOBK8jG"
          ],
          "x": 912.4442,
          "y": 1384.9028,
          "direction": 2
        },
        "end": {
          "tableId": "ljgpQ-ut5b5LoN7vA-yQR",
          "columnIds": [
            "xISgtW271xZI0_lnOe2DX"
          ],
          "x": 1168.3029,
          "y": 1384.4506,
          "direction": 1
        },
        "meta": {
          "updateAt": 1729268150379,
          "createAt": 1729268150379
        }
      },
      "9uzg_thkkvkO2CZzfIQIo": {
        "id": "9uzg_thkkvkO2CZzfIQIo",
        "identification": false,
        "relationshipType": 16,
        "startRelationshipType": 2,
        "start": {
          "tableId": "ic8qI8cXoM7FoDHA6eZO2",
          "columnIds": [
            "IYAlhJTjLLLQUrJ-S_j5A"
          ],
          "x": 609.6368,
          "y": 760.3357,
          "direction": 8
        },
        "end": {
          "tableId": "LQ6xqThd9sB75yziJ29q4",
          "columnIds": [
            "bNUV89eVjQaxI5Xj33ik-"
          ],
          "x": 613.0531,
          "y": 900.7208,
          "direction": 4
        },
        "meta": {
          "updateAt": 1729269415032,
          "createAt": 1729269415032
        }
      },
      "EBDhVi0rQCXI6npZn5ENY": {
        "id": "EBDhVi0rQCXI6npZn5ENY",
        "identification": false,
        "relationshipType": 16,
        "startRelationshipType": 2,
        "start": {
          "tableId": "LQ6xqThd9sB75yziJ29q4",
          "columnIds": [
            "-MGcSurd8FjR7kvvOnydf"
          ],
          "x": 808.0531,
          "y": 900.7208,
          "direction": 4
        },
        "end": {
          "tableId": "ic8qI8cXoM7FoDHA6eZO2",
          "columnIds": [
            "Xq9_PHOLJjaFhQzoVvFzM"
          ],
          "x": 812.1368,
          "y": 760.3357,
          "direction": 8
        },
        "meta": {
          "updateAt": 1729698722856,
          "createAt": 1729698722856
        }
      },
      "X_B49gYJP8Ir3YxUyhfeB": {
        "id": "X_B49gYJP8Ir3YxUyhfeB",
        "identification": false,
        "relationshipType": 16,
        "startRelationshipType": 2,
        "start": {
          "tableId": "IVFL0tVOqoKbhTHys2c68",
          "columnIds": [
            "a2Ylt0NMtvJaB4V9I-bzp"
          ],
          "x": 913.5047999999999,
          "y": 173.8375,
          "direction": 2
        },
        "end": {
          "tableId": "nI60JygSC7yhleBHLTc_E",
          "columnIds": [
            "UB-KSMm4ddqKQ3X8TJj4p"
          ],
          "x": 1026.8293,
          "y": 172.1953,
          "direction": 1
        },
        "meta": {
          "updateAt": 1730228584192,
          "createAt": 1730228584192
        }
      }
    },
    "indexEntities": {},
    "indexColumnEntities": {},
    "memoEntities": {}
  },
  "lww": {
    "IVFL0tVOqoKbhTHys2c68": [
      "tableEntities",
      1729267035613,
      -1,
      {
        "name": 1730226679194
      }
    ],
    "hYEQ0o8cybYRYyJaygNWA": [
      "tableColumnEntities",
      1729267051019,
      1729267112818,
      {}
    ],
    "ic8qI8cXoM7FoDHA6eZO2": [
      "tableEntities",
      1729267061374,
      -1,
      {
        "name": 1730226767752
      }
    ],
    "a2Ylt0NMtvJaB4V9I-bzp": [
      "tableColumnEntities",
      1729267112723,
      -1,
      {
        "options(primaryKey)": 1729267112723,
        "name": 1729703974994,
        "dataType": 1729703978808
      }
    ],
    "AeuHd-sdgcfEAIFrLRtzc": [
      "tableColumnEntities",
      1729267117056,
      1729267737703,
      {}
    ],
    "LQ6xqThd9sB75yziJ29q4": [
      "tableEntities",
      1729267148685,
      -1,
      {
        "name": 1730226623529
      }
    ],
    "dPNIQ1drtSQcs5zYD5J6k": [
      "tableEntities",
      1729267312801,
      -1,
      {
        "name": 1730226571594
      }
    ],
    "UTWwgy9OiObGfYdOBK8jG": [
      "tableColumnEntities",
      1729267329515,
      -1,
      {
        "options(primaryKey)": 1729267329515,
        "name": 1729704984313
      }
    ],
    "8-0oERPNzY8WVxk0RaI4j": [
      "tableColumnEntities",
      1729267330992,
      -1,
      {
        "options(notNull)": 1729267330992,
        "name": 1729707168803,
        "dataType": 1729267330992,
        "default": 1729267330992,
        "comment": 1729267330992
      }
    ],
    "YtyghDogwvJ3JZTZeYz0H": [
      "relationshipEntities",
      1729267330992,
      -1,
      {}
    ],
    "9TMxcuD0BUhpN_NJtKaI_": [
      "tableColumnEntities",
      1729704728215,
      1729704727440,
      {
        "options(notNull)": 1729267535215,
        "name": 1729707146996,
        "dataType": 1729703978808,
        "default": 1729267535215,
        "comment": 1729267535215
      }
    ],
    "GAlHyIcNQf2h2XprNrvaA": [
      "relationshipEntities",
      1729704728215,
      1729704727440,
      {}
    ],
    "AblPsS5f9kFkxgnlNHuR4": [
      "tableEntities",
      1729267594938,
      -1,
      {
        "name": 1730225950834
      }
    ],
    "0aqdazY0rmgx7ASNWK84R": [
      "tableColumnEntities",
      1729267600595,
      1729268011290,
      {}
    ],
    "h5wO3PYGvf-QvEnUodwWD": [
      "tableEntities",
      1729267603794,
      -1,
      {
        "name": 1730226197625
      }
    ],
    "MZzQgWsKLlCjdaTvkv_5n": [
      "tableEntities",
      1729267633854,
      -1,
      {
        "name": 1730226275527
      }
    ],
    "vlOwlrHNzAnlBEOfDUz3H": [
      "tableColumnEntities",
      1729267683602,
      -1,
      {
        "options(primaryKey)": 1729267683602,
        "name": 1729704304732,
        "dataType": 1729704372591
      }
    ],
    "TUg0Y3dWTCk29vCSmQFfS": [
      "tableColumnEntities",
      1729267685615,
      -1,
      {
        "options(notNull)": 1729267685615,
        "name": 1729705418082,
        "dataType": 1729704372591,
        "default": 1729267685615,
        "comment": 1729267685615
      }
    ],
    "D-B-0aQD1qJvD6PizE4gx": [
      "relationshipEntities",
      1729267685615,
      -1,
      {}
    ],
    "H9E7zl7N7p9CNQrdVxmuU": [
      "tableColumnEntities",
      1729267715357,
      1729267741607,
      {}
    ],
    "SQD28Msh3wGhA4fl0rNt_": [
      "tableColumnEntities",
      1729268171434,
      1729268170259,
      {
        "options(notNull)": 1729267725918,
        "name": 1729707300108,
        "dataType": 1729704372591,
        "default": 1729267725918,
        "comment": 1729267725918
      }
    ],
    "Tw-aKEz6HEb7VwFdhW5wL": [
      "relationshipEntities",
      1729268171434,
      1729268170259,
      {}
    ],
    "PZABfmy4YQI78cd8GmzKI": [
      "tableEntities",
      1729267928704,
      -1,
      {
        "name": 1730226475863
      }
    ],
    "nyOI0O3XLXTc96FCJCwZx": [
      "tableColumnEntities",
      1729267936902,
      1729267952164,
      {}
    ],
    "NTClLTXslrBVfs_hfnIwW": [
      "tableColumnEntities",
      1729703893219,
      1729703892052,
      {
        "options(primaryKey)": 1729267948992,
        "name": 1729704003741,
        "dataType": 1729704022816
      }
    ],
    "pUcs85xaL2-tF5Mlo2jyS": [
      "tableColumnEntities",
      1729267950797,
      -1,
      {
        "options(notNull)": 1729267950797,
        "name": 1729707278535,
        "dataType": 1729704022816,
        "default": 1729267950797,
        "comment": 1729267950797
      }
    ],
    "qDMuPz6jUjd1DgoRAvS09": [
      "relationshipEntities",
      1729703893219,
      1729703892052,
      {}
    ],
    "nWRI1Fpaj_fn8Uwt67FQ8": [
      "tableColumnEntities",
      1729268007702,
      -1,
      {
        "options(primaryKey)": 1729268007702,
        "name": 1729704418548,
        "dataType": 1729704502521
      }
    ],
    "Lzi4Dove5noE9Hye7q6st": [
      "tableColumnEntities",
      1729268009127,
      -1,
      {
        "options(notNull)": 1729268009127,
        "name": 1729707266405,
        "dataType": 1729704502521,
        "default": 1729268009127,
        "comment": 1729268009127
      }
    ],
    "s3Q9bL-xfkaLt2zN3n2lD": [
      "relationshipEntities",
      1729268009127,
      -1,
      {}
    ],
    "ljgpQ-ut5b5LoN7vA-yQR": [
      "tableEntities",
      1729268053899,
      -1,
      {
        "name": 1730226522713
      }
    ],
    "ikq-YP-qxaD-XxkVSaS1Q": [
      "tableColumnEntities",
      1729268066335,
      1729268093373,
      {}
    ],
    "Oq66Upuo2UT2nBchDN9dJ": [
      "tableColumnEntities",
      1729268091800,
      -1,
      {
        "options(notNull)": 1729268091800,
        "name": 1729707230286,
        "dataType": 1729704022816,
        "default": 1729268091800,
        "comment": 1729268091800
      }
    ],
    "DNH8VKpvUj_2M8NjpsrM-": [
      "relationshipEntities",
      1729703893219,
      1729703892052,
      {}
    ],
    "gKaUAx6CC5TvsVWTKbYWn": [
      "tableColumnEntities",
      1729268139589,
      -1,
      {
        "options(notNull)": 1729268139589,
        "name": 1729707200564,
        "dataType": 1729704502521,
        "default": 1729268139589,
        "comment": 1729268139589
      }
    ],
    "R1oOn_lrzmAo17E1Up3Ye": [
      "relationshipEntities",
      1729268139589,
      -1,
      {}
    ],
    "xISgtW271xZI0_lnOe2DX": [
      "tableColumnEntities",
      1729268150376,
      -1,
      {
        "options(notNull)": 1729268150376,
        "name": 1729707216393,
        "dataType": 1729268150376,
        "default": 1729268150376,
        "comment": 1729268150376
      }
    ],
    "ojau24ldOTQOe6yNscmGW": [
      "relationshipEntities",
      1729268150376,
      -1,
      {}
    ],
    "9HuYrSze1wzzUN69Bn73Y": [
      "tableColumnEntities",
      1729268170259,
      1729268171434,
      {
        "name": 1729268170259,
        "dataType": 1729268170259,
        "default": 1729268170259,
        "comment": 1729268170259,
        "options(primaryKey)": 1729268170259,
        "options(notNull)": 1729268170259,
        "options(unique)": 1729268170259,
        "options(autoIncrement)": 1729268170259
      }
    ],
    "settings.databaseName": [
      "settings",
      -1,
      -1,
      {
        "databaseName": 1729268440366
      }
    ],
    "IYAlhJTjLLLQUrJ-S_j5A": [
      "tableColumnEntities",
      1729269413819,
      -1,
      {
        "options(primaryKey)": 1729269413819,
        "name": 1729703909798,
        "dataType": 1729706347497
      }
    ],
    "bNUV89eVjQaxI5Xj33ik-": [
      "tableColumnEntities",
      1729269415027,
      -1,
      {
        "options(notNull)": 1729269415027,
        "name": 1729707107580,
        "dataType": 1729706347497,
        "default": 1729269415027,
        "comment": 1729269415027
      }
    ],
    "9uzg_thkkvkO2CZzfIQIo": [
      "relationshipEntities",
      1729269415027,
      -1,
      {}
    ],
    "EcFzv1jwP6GmVaPSe0h08": [
      "tableColumnEntities",
      1729698703798,
      1729704822842,
      {
        "options(notNull)": 1729698703798,
        "name": 1729698703798,
        "dataType": 1729698703798,
        "default": 1729698703798,
        "comment": 1729698703798
      }
    ],
    "-MGcSurd8FjR7kvvOnydf": [
      "tableColumnEntities",
      1729698720207,
      -1,
      {
        "options(primaryKey)": 1729698720207,
        "name": 1729704839685,
        "dataType": 1729704957658
      }
    ],
    "Xq9_PHOLJjaFhQzoVvFzM": [
      "tableColumnEntities",
      1729704725778,
      1729704724648,
      {
        "options(notNull)": 1729698722855,
        "name": 1729707617864,
        "dataType": 1729704957658,
        "default": 1729698722855,
        "comment": 1729698722855
      }
    ],
    "EBDhVi0rQCXI6npZn5ENY": [
      "relationshipEntities",
      1729704725778,
      1729704724648,
      {}
    ],
    "5kJQPXpyhUS1doRa_BEKv": [
      "tableColumnEntities",
      1729701799712,
      1729703976557,
      {
        "name": 1729702227030,
        "dataType": 1729701868830,
        "default": 1729701838025,
        "options(notNull)": 1729702102218,
        "options(primaryKey)": 1729703094771
      }
    ],
    "aJTMV8sFMZRYyeR5iz8Qi": [
      "tableColumnEntities",
      1729701872585,
      -1,
      {
        "name": 1729702314889,
        "dataType": 1729702054842,
        "options(notNull)": 1729702107727
      }
    ],
    "DX0OA5goKXQJeX7f-SeRg": [
      "tableColumnEntities",
      1729701883462,
      -1,
      {
        "name": 1729702355668,
        "dataType": 1729702057682,
        "options(notNull)": 1729702108553
      }
    ],
    "PuRQlQEBGGJI17X9vnYBH": [
      "tableColumnEntities",
      1729701897943,
      -1,
      {
        "name": 1729702492889,
        "dataType": 1729701946913,
        "options(notNull)": 1729702109350
      }
    ],
    "EDrVmf-w0ipe4MZ5NoAJF": [
      "tableColumnEntities",
      1729701903860,
      -1,
      {
        "name": 1729702413038,
        "dataType": 1729701957988,
        "options(notNull)": 1729702110039
      }
    ],
    "EQwX-3e3hikkLxuLDb8i3": [
      "tableColumnEntities",
      1729702536586,
      1729703915817,
      {
        "name": 1729703069765,
        "options(primaryKey)": 1729703098109,
        "dataType": 1729703163032
      }
    ],
    "9-xFfkpsAbXJQd_HI7g2m": [
      "tableColumnEntities",
      1729702701859,
      -1,
      {
        "name": 1729703078575,
        "dataType": 1729703159057
      }
    ],
    "zXKxytADtc7w7wjwUQ4Bx": [
      "tableColumnEntities",
      1729702732718,
      1729702730559,
      {
        "name": 1729703130886,
        "dataType": 1729703167587
      }
    ],
    "lVJ7BHwsMrEpcnmh782vG": [
      "tableColumnEntities",
      1729702721906,
      -1,
      {
        "name": 1729703138914,
        "dataType": 1729703169639
      }
    ],
    "FPsmcP2g66A0veDbreDWP": [
      "tableColumnEntities",
      1729702737757,
      -1,
      {
        "name": 1729703145810,
        "dataType": 1729703172537
      }
    ],
    "yfE7Ssgx-mKwZ3ANDU-mr": [
      "tableColumnEntities",
      1729702748928,
      -1,
      {
        "name": 1729703151512,
        "dataType": 1729703176175
      }
    ],
    "3GXytbJ6ph_zehmFc5wx4": [
      "tableColumnEntities",
      1729703755549,
      1729704020716,
      {
        "name": 1729703763335
      }
    ],
    "LElIDzWJvLxWLpr_NWUMk": [
      "tableColumnEntities",
      1729703764993,
      -1,
      {
        "name": 1729704053893,
        "dataType": 1729704513349
      }
    ],
    "9Lwd3sYJLSWsJpqhPY778": [
      "tableColumnEntities",
      1729703773438,
      -1,
      {
        "name": 1729704060702,
        "dataType": 1729704515065
      }
    ],
    "-VXeuBq5RV4Vr134u3OQF": [
      "tableColumnEntities",
      1729703782575,
      1729703791899,
      {}
    ],
    "eJbChfbITolz3Q1Hc8c1f": [
      "tableColumnEntities",
      1729704244647,
      -1,
      {
        "name": 1729704266294,
        "dataType": 1729704312234
      }
    ],
    "OPEWIraV2yNTD6syGf2fE": [
      "tableColumnEntities",
      1729704251528,
      -1,
      {
        "name": 1729704272545,
        "dataType": 1729704314859
      }
    ],
    "4mI15uUm-aUd3cIgozEhM": [
      "tableColumnEntities",
      1729704393259,
      -1,
      {
        "name": 1729704470892,
        "dataType": 1729704505758
      }
    ],
    "eMpdEQ5KRJy8xPiDJ0WL0": [
      "tableColumnEntities",
      1729704393954,
      -1,
      {
        "name": 1729704477506,
        "dataType": 1729704507535
      }
    ],
    "nXNpNPFYx3_H1hB0Bz6iA": [
      "tableColumnEntities",
      1729704944589,
      -1,
      {
        "name": 1729704994631
      }
    ],
    "E6LG2TtoI7PNjHeu54vl4": [
      "tableColumnEntities",
      1729704945275,
      -1,
      {
        "name": 1729705005201
      }
    ],
    "-Jjf8jIkfxvKlw_mz9Ypw": [
      "tableColumnEntities",
      1729705144074,
      -1,
      {
        "name": 1729705158478,
        "dataType": 1729705163064
      }
    ],
    "nI60JygSC7yhleBHLTc_E": [
      "tableEntities",
      1730228316302,
      -1,
      {
        "name": 1730229137396
      }
    ],
    "TO8Ug-uteTAYxIETYvl7_": [
      "tableColumnEntities",
      1730228367518,
      -1,
      {
        "name": 1730228460138,
        "dataType": 1730228438886
      }
    ],
    "3cHZ9bpPHqcnxHb64mxd_": [
      "tableColumnEntities",
      1730228444326,
      -1,
      {
        "name": 1730228465737,
        "dataType": 1730228520135
      }
    ],
    "AW8gWTXUejkiMFlAMrx5z": [
      "tableColumnEntities",
      1730228468734,
      -1,
      {
        "name": 1730228530264,
        "dataType": 1730228548838
      }
    ],
    "YB-p2ZOJRiBcH1ql7eTuq": [
      "tableColumnEntities",
      1730228555838,
      -1,
      {
        "name": 1730228569034,
        "dataType": 1730228853244
      }
    ],
    "UB-KSMm4ddqKQ3X8TJj4p": [
      "tableColumnEntities",
      1730228584189,
      -1,
      {
        "options(notNull)": 1730228584189,
        "name": 1730228584189,
        "dataType": 1730228584189,
        "default": 1730228584189,
        "comment": 1730228584189
      }
    ],
    "X_B49gYJP8Ir3YxUyhfeB": [
      "relationshipEntities",
      1730228584189,
      -1,
      {}
    ],
    "8Xp6kiOqRt7VACes79SwC": [
      "tableColumnEntities",
      1730228605262,
      -1,
      {
        "name": 1730228638827,
        "dataType": 1730228846660
      }
    ],
    "cvObatuMh3ENwEZnzgXWh": [
      "tableColumnEntities",
      1730228643950,
      -1,
      {
        "name": 1730228655991,
        "dataType": 1730228843044
      }
    ],
    "-9YTMjEZIjexsprzBUQXC": [
      "tableColumnEntities",
      1730228704094,
      -1,
      {
        "name": 1730228719369,
        "dataType": 1730228832244
      }
    ],
    "Bjzuj4fKIRR40wUjw8wcA": [
      "tableColumnEntities",
      1730228734021,
      -1,
      {
        "name": 1730228749387,
        "dataType": 1730228838707
      }
    ],
    "89AOnOlBrzl1U52eLgSDI": [
      "tableColumnEntities",
      1730228767781,
      -1,
      {
        "name": 1730228790838,
        "dataType": 1730228823756
      }
    ],
    "fer33Y7k_muAm2eOPpxdg": [
      "tableColumnEntities",
      1730228799629,
      -1,
      {
        "name": 1730228812936,
        "dataType": 1730228819460
      }
    ]
  }
}